{"stats":{"minecraft:used":{"reinforceditems:reinforcedobsidian":48,"minecraft:diamond_pickaxe":1,"minecraft:sandstone":2,"minecraft:crafting_table":1},"minecraft:mined":{"reinforceditems:reinforcedobsidian":1},"minecraft:custom":{"minecraft:jump":22,"minecraft:time_since_rest":7372,"minecraft:crouch_one_cm":556,"minecraft:play_one_minute":7372,"minecraft:leave_game":5,"minecraft:time_since_death":7372,"minecraft:walk_one_cm":7310,"minecraft:sneak_time":421,"minecraft:interact_with_crafting_table":4},"minecraft:crafted":{"reinforceditems:reinforcedobsidian":17,"reinforceditems:obsidianchunk":585}},"DataVersion":1976}